st_card_component/__init__.py
st_card_component/frontend/build/asset-manifest.json
st_card_component/frontend/build/bootstrap.min.css
st_card_component/frontend/build/index.html
st_card_component/frontend/build/static/css/main.4aa27459.css
st_card_component/frontend/build/static/css/main.4aa27459.css.map
st_card_component/frontend/build/static/js/main.0586419d.js
st_card_component/frontend/build/static/js/main.0586419d.js.LICENSE.txt
st_card_component/frontend/build/static/js/main.0586419d.js.map
st_card_component/frontend/build/static/media/roboto-cyrillic-300-normal.1431d1cef06ad04f5458.woff2
st_card_component/frontend/build/static/media/roboto-cyrillic-300-normal.5b5f2f31962967dfc22c.woff
st_card_component/frontend/build/static/media/roboto-cyrillic-400-normal.71a33b6b50457b2c903a.woff2
st_card_component/frontend/build/static/media/roboto-cyrillic-400-normal.c1d66054fe23e181d92c.woff
st_card_component/frontend/build/static/media/roboto-cyrillic-500-normal.965aebef74db72eaf236.woff
st_card_component/frontend/build/static/media/roboto-cyrillic-500-normal.cad7d3d9cb265e334e58.woff2
st_card_component/frontend/build/static/media/roboto-cyrillic-700-normal.d010f1f324e111a22e53.woff2
st_card_component/frontend/build/static/media/roboto-cyrillic-700-normal.f8a034d72aa6828199d4.woff
st_card_component/frontend/build/static/media/roboto-cyrillic-ext-300-normal.3503ec5cc6330e21f695.woff
st_card_component/frontend/build/static/media/roboto-cyrillic-ext-300-normal.4777461b144e55145268.woff2
st_card_component/frontend/build/static/media/roboto-cyrillic-ext-400-normal.804378952da8a10faae2.woff2
st_card_component/frontend/build/static/media/roboto-cyrillic-ext-400-normal.af4d91666ea345601bea.woff
st_card_component/frontend/build/static/media/roboto-cyrillic-ext-500-normal.268f264f58eba5c07c88.woff
st_card_component/frontend/build/static/media/roboto-cyrillic-ext-500-normal.62ced72e5832f02c2796.woff2
st_card_component_sssua-0.0.1.dist-info/LICENSE
st_card_component_sssua-0.0.1.dist-info/METADATA
st_card_component_sssua-0.0.1.dist-info/WHEEL
st_card_component_sssua-0.0.1.dist-info/top_level.txt
st_card_component_sssua-0.0.1.dist-info/RECORD
